easy_as_pypi/__init__.py
easy_as_pypi/commands/__init__.py
easy_as_pypi/commands/easy_as_pypi.py
easy_as_pypi/locale/babel.cfg
easy_as_pypi/locale/de/LC_MESSAGES/messages.mo
easy_as_pypi/locale/de/LC_MESSAGES/messages.po
easy_as_pypi/locale/en/LC_MESSAGES/messages.mo
easy_as_pypi/locale/en/LC_MESSAGES/messages.po
easy_as_pypi/locale/messages.pot
easy_as_pypi-1.1.19.dist-info/LICENSE
easy_as_pypi-1.1.19.dist-info/METADATA
easy_as_pypi-1.1.19.dist-info/WHEEL
easy_as_pypi-1.1.19.dist-info/entry_points.txt
easy_as_pypi-1.1.19.dist-info/RECORD
